setup.cfg
setup.py
katastrophe/__init__.py
katastrophe/katastrophe.py
katastrophe/latest.py
katastrophe/subcategories.py
katastrophe.egg-info/PKG-INFO
katastrophe.egg-info/SOURCES.txt
katastrophe.egg-info/dependency_links.txt
katastrophe.egg-info/entry_points.txt
katastrophe.egg-info/requires.txt
katastrophe.egg-info/top_level.txt