Metadata-Version: 1.1
Name: katastrophe
Version: 1.1.9
Summary: Download torrents from kat.ph directly through terminal
Home-page: https://github.com/alyakhtar/katastrophe
Author: Aly Akhtar
Author-email: samurai.aly@gmail.com
License: MIT
Download-URL: https://github.com/alyakhtar/mypackage/tarball/1.1.5
Keywords: torrent,download,kat.ph
Platform: UNKNOWN
